MANIFEST.in
README.rst
constraints.txt
constraints_plone52.txt
constraints_plone60.txt
requirements.txt
requirements_plone52.txt
requirements_plone60.txt
setup.py
docs/HISTORY.txt
docs/LICENSE.GPL
docs/LICENSE.txt
docs/TODO.txt
docs/notes.txt
src/collective/__init__.py
src/collective.pdfjs.egg-info/PKG-INFO
src/collective.pdfjs.egg-info/SOURCES.txt
src/collective.pdfjs.egg-info/dependency_links.txt
src/collective.pdfjs.egg-info/entry_points.txt
src/collective.pdfjs.egg-info/namespace_packages.txt
src/collective.pdfjs.egg-info/not-zip-safe
src/collective.pdfjs.egg-info/requires.txt
src/collective.pdfjs.egg-info/top_level.txt
src/collective/pdfjs/__init__.py
src/collective/pdfjs/configure.zcml
src/collective/pdfjs/setuphandlers.py
src/collective/pdfjs/testing.py
src/collective/pdfjs/tests.py
src/collective/pdfjs/browser/__init__.py
src/collective/pdfjs/browser/configure.zcml
src/collective/pdfjs/browser/fileviews.py
src/collective/pdfjs/browser/interfaces.py
src/collective/pdfjs/browser/resources/compatibility.js
src/collective/pdfjs/browser/resources/l10n.js
src/collective/pdfjs/browser/resources/locale.properties
src/collective/pdfjs/browser/resources/pdf.js
src/collective/pdfjs/browser/resources/ploneintegration.js
src/collective/pdfjs/browser/resources/viewer.css
src/collective/pdfjs/browser/resources/viewer.js
src/collective/pdfjs/browser/resources/images/annotation-check.svg
src/collective/pdfjs/browser/resources/images/annotation-comment.svg
src/collective/pdfjs/browser/resources/images/annotation-help.svg
src/collective/pdfjs/browser/resources/images/annotation-note.svg
src/collective/pdfjs/browser/resources/images/findbarButton-next-rtl.png
src/collective/pdfjs/browser/resources/images/findbarButton-next.png
src/collective/pdfjs/browser/resources/images/findbarButton-previous-rtl.png
src/collective/pdfjs/browser/resources/images/findbarButton-previous.png
src/collective/pdfjs/browser/resources/images/loading-icon.gif
src/collective/pdfjs/browser/resources/images/loading-small.png
src/collective/pdfjs/browser/resources/images/texture.png
src/collective/pdfjs/browser/resources/images/toolbarButton-bookmark.png
src/collective/pdfjs/browser/resources/images/toolbarButton-download.png
src/collective/pdfjs/browser/resources/images/toolbarButton-fullscreen.png
