Metadata-Version: 2.1
Name: collective.pdfjs
Version: 1.0.3
Summary: pdf.js integration for Plone
Home-page: http://pypi.python.org/pypi/collective.pdfjs
Author: zedr
Author-email: zedr@zedr.com
License: GPL
Keywords: plone zope pdf JavaScript
Platform: UNKNOWN
Classifier: Environment :: Web Environment
Classifier: Framework :: Plone
Classifier: Framework :: Plone :: Addon
Classifier: Programming Language :: Python
Classifier: Framework :: Plone :: 6.0
Classifier: Programming Language :: Python :: 3.8
Classifier: Programming Language :: Python :: 3.9
Classifier: Programming Language :: Python :: 3.10
Classifier: Operating System :: OS Independent
Classifier: License :: OSI Approved :: GNU General Public License v2 (GPLv2)
Provides-Extra: test
